HowdenLLM/__init__.py
HowdenLLM/manager.py
HowdenLLM/providers/__init__.py
HowdenLLM/providers/base_provider.py
HowdenLLM/providers/provider_factory.py
HowdenLLM/providers/provider_huggingface.py
HowdenLLM/providers/provider_meta.py
HowdenLLM/providers/provider_openai.py
howdenllm-1.3.0.dist-info/METADATA
howdenllm-1.3.0.dist-info/WHEEL
howdenllm-1.3.0.dist-info/RECORD
