Metadata-Version: 2.4
Name: HowdenLLM
Version: 1.3.0
Summary: A simple configuration manager with Pydantic and JSON export.
License: MIT
Keywords: config,configuration,pydantic,json
Author: JesperThoftIllemannJ
Author-email: jesper.jaeger@howdendanmark.dk
Requires-Python: >=3.12,<3.14
Classifier: License :: OSI Approved :: MIT License
Classifier: Programming Language :: Python :: 3
Classifier: Programming Language :: Python :: 3.12
Classifier: Programming Language :: Python :: 3.13
Requires-Dist: accelerate (>=1.10.0,<2.0.0)
Requires-Dist: langchain (>=1.1.3,<2.0.0)
Requires-Dist: langchain-community (>=0.3.27,<0.4.0)
Requires-Dist: openai (>=1.99.9,<2.0.0)
Requires-Dist: pydantic (>=2.11.7,<3.0.0)
Requires-Dist: pytest (>=9.0.2,<10.0.0)
Requires-Dist: python-dotenv (>=1.1.1,<2.0.0)
Requires-Dist: tiktoken (>=0.12.0,<0.13.0)
Requires-Dist: transformers (>=4.55.0,<5.0.0)
Project-URL: Documentation, https://github.com/yourusername/config
Project-URL: Homepage, https://github.com/yourusername/config
Project-URL: Repository, https://github.com/yourusername/config
